{
  "designation": [
    {
      "designation": "test",
      "id": 2
    },
    {
      "designation": "test2",
      "id": 3
    }
  ],
  "newMember": [
    {
      "memberDetail": {
        "fname": "s",
        "lname": "s",
        "image": "C:\\fakepath\\img.7jpg.jpg"
      }
    }
  ],
  "customerId": [
    {
      "id": 1,
      "cId": 1007
    }
  ],
  "customers": [
    {
      "customerDetail": {
        "cId": "C1002",
        "cName": "kishor",
        "cLName": "Thapa",
        "cPhone": "6314807913",
        "cEmail": "iamkishorshrestha@gmail.com",
        "cDob": "2023-10-02T04:00:00.000Z",
        "cGender": "male"
      },
      "customerAddress": {
        "cAddress": "9730 57th Avenue",
        "cApartment": "",
        "cCity": "new york",
        "cState": "Alabama",
        "cZipcode": "11368"
      },
      "id": 3
    },
    {
      "customerDetail": {
        "cId": "C1004",
        "cName": "Tested",
        "cLName": "Test",
        "cPhone": "4141715171",
        "cEmail": "haah@gamail.com",
        "cDob": "",
        "cGender": "female"
      },
      "customerAddress": {
        "cAddress": "4720 parkmount dr",
        "cApartment": "",
        "cCity": "fort worth",
        "cState": "Arkansas",
        "cZipcode": "76317"
      },
      "id": 4
    },
    {
      "customerDetail": {
        "cId": "C1005",
        "cName": "kishor",
        "cLName": "shrestha",
        "cPhone": "6314807913",
        "cEmail": "iamkishorshrestha@gmail.com",
        "cDob": "",
        "cGender": "male"
      },
      "customerAddress": {
        "cAddress": "9730 57th Avenue",
        "cApartment": "",
        "cCity": "new york",
        "cState": "Arkansas",
        "cZipcode": "11368"
      },
      "id": 5
    }
  ],
  "brand": [
    {
      "brand": "test",
      "logo": null,
      "id": 1
    },
    {
      "brand": "1",
      "logo": null,
      "id": 2
    },
    {
      "brand": "2",
      "logo": null,
      "id": 3
    },
    {
      "brand": "3",
      "logo": null,
      "id": 4
    },
    {
      "brand": "4",
      "logo": null,
      "id": 5
    },
    {
      "brand": "5",
      "logo": null,
      "id": 6
    }
  ],
  "member": [
    {
      "fname": "Test",
      "lname": "test",
      "image": "C:\\fakepath\\71Q5ZhQxgFL._AC_SX569_.jpg",
      "id": 1
    },
    {
      "fname": "qq",
      "lname": "qq",
      "image": "C:\\fakepath\\71Q5ZhQxgFL._AC_SX569_.jpg",
      "id": 2
    },
    {
      "id": 3
    },
    {
      "id": 4
    },
    {
      "fname": "s",
      "lname": "s",
      "image": "C:\\fakepath\\71Q5ZhQxgFL._AC_SX569_.jpg",
      "id": 5
    },
    {
      "fname": "aa",
      "lname": "aa",
      "image": "C:\\fakepath\\71Q5ZhQxgFL._AC_SX569_.jpg",
      "id": 6
    },
    {
      "fname": "k",
      "lname": "m",
      "image": "C:\\fakepath\\71Q5ZhQxgFL._AC_SX569_.jpg",
      "id": 7
    },
    {
      "id": 8
    },
    {
      "id": 9
    }
  ]
}